valemo_data_query/__init__.py
valemo_data_query/_azure_gen2.py
valemo_data_query/_user_credentials.py
valemo_data_query/user_credentials.json
valemo_data_query-1.0.1.dist-info/License.txt
valemo_data_query-1.0.1.dist-info/METADATA
valemo_data_query-1.0.1.dist-info/WHEEL
valemo_data_query-1.0.1.dist-info/top_level.txt
valemo_data_query-1.0.1.dist-info/RECORD
