Metadata-Version: 2.1
Name: valemo-data-query
Version: 1.0.1
Summary: UNKNOWN
Home-page: UNKNOWN
Author: Arthur_LAFFARGUE
Author-email: arthur.laffargue@valemo.fr
License: GNU
Platform: UNKNOWN
License-File: License.txt
Requires-Dist: pandas
Requires-Dist: azure-storage-file-datalake
Requires-Dist: numpy
Requires-Dist: parquet
